setup.py
binify/__init__.py
binify/binify.py
binify/cli.py
binify.egg-info/PKG-INFO
binify.egg-info/SOURCES.txt
binify.egg-info/dependency_links.txt
binify.egg-info/entry_points.txt
binify.egg-info/requires.txt
binify.egg-info/top_level.txt
binify/shapegrids/__init__.py
binify/shapegrids/hexagon.py
binify/shapegrids/shapegrid.py