Metadata-Version: 1.0
Name: binify
Version: 0.1.6
Summary: A command-line tool to better visualize crowded dot density maps.
Home-page: http://www.kevinschaul.com
Author: Kevin Schaul
Author-email: kevin.schaul@gmail.com
License: MIT
Platform: UNKNOWN
Classifier: Development Status :: 4 - Beta
Classifier: Environment :: Console
Classifier: Intended Audience :: Developers
Classifier: License :: OSI Approved :: MIT License
Classifier: Natural Language :: English
Classifier: Operating System :: Unix
Classifier: Programming Language :: Python
Classifier: Topic :: Software Development
